{
  "TotalCycles": 20000,
  "SimulationTime": "26m41.515472519s",
  "CyclesPerSecond": 12.48817157447895,
  "PacketsPerSecond": 42.49599905079442,
  "NumPacketsReceived": 68413,
  "NumPacketsTransmitted": 68058,
  "Throughput": 0.0531703125,
  "AveragePacketDelay": 81.97865056275529,
  "AveragePacketHops": 6.976226160039966,
  "MaxPacketDelay": 728,
  "MaxPacketHops": 15,
  "NumPayloadPacketsReceived": 68167,
  "NumPayloadPacketsTransmitted": 67812,
  "PayloadThroughput": 0.052978125,
  "AveragePayloadPacketDelay": 82.0367191647496,
  "AveragePayloadPacketHops": 6.977408128354863,
  "MaxPayloadPacketDelay": 728,
  "MaxPayloadPacketHops": 15,
  "AverageFlitPerStateDelay[INPUT_BUFFER]": 4.497121983967978,
  "AverageFlitPerStateDelay[ROUTE_COMPUTATION]": 1.8033071213346072,
  "AverageFlitPerStateDelay[VIRTUAL_CHANNEL_ALLOCATION]": 1.2435874552460549,
  "AverageFlitPerStateDelay[SWITCH_ALLOCATION]": 1,
  "AverageFlitPerStateDelay[SWITCH_TRAVERSAL]": 1.1662162176428919,
  "AverageFlitPerStateDelay[LINK_TRAVERSAL]": 4.460308590137512,
  "AverageFlitPerStateDelay[DESTINATION_ARRIVED]": 0,
  "MaxFlitPerStateDelay[INPUT_BUFFER]": 132,
  "MaxFlitPerStateDelay[ROUTE_COMPUTATION]": 103,
  "MaxFlitPerStateDelay[VIRTUAL_CHANNEL_ALLOCATION]": 5,
  "MaxFlitPerStateDelay[SWITCH_ALLOCATION]": 1,
  "MaxFlitPerStateDelay[SWITCH_TRAVERSAL]": 103,
  "MaxFlitPerStateDelay[LINK_TRAVERSAL]": 177,
  "MaxFlitPerStateDelay[DESTINATION_ARRIVED]": 0
}