{
  "TotalCycles": 20000,
  "SimulationTime": "1m14.516682656s",
  "CyclesPerSecond": 268.3962743259562,
  "PacketsPerSecond": 254.50676712958798,
  "NumPacketsReceived": 19002,
  "NumPacketsTransmitted": 18965,
  "Throughput": 0.01481640625,
  "AveragePacketDelay": 37.77975217505932,
  "AveragePacketHops": 6.303295544423939,
  "MaxPacketDelay": 82,
  "MaxPacketHops": 15,
  "NumPayloadPacketsReceived": 19002,
  "NumPayloadPacketsTransmitted": 18965,
  "PayloadThroughput": 0.01481640625,
  "AveragePayloadPacketDelay": 37.77975217505932,
  "AveragePayloadPacketHops": 6.303295544423939,
  "MaxPayloadPacketDelay": 82,
  "MaxPayloadPacketHops": 15,
  "AverageFlitPerStateDelay[INPUT_BUFFER]": 2.166617239190002,
  "AverageFlitPerStateDelay[ROUTE_COMPUTATION]": 1.0006932843301035,
  "AverageFlitPerStateDelay[VIRTUAL_CHANNEL_ALLOCATION]": 1.0147263964182196,
  "AverageFlitPerStateDelay[SWITCH_ALLOCATION]": 1,
  "AverageFlitPerStateDelay[SWITCH_TRAVERSAL]": 1,
  "AverageFlitPerStateDelay[LINK_TRAVERSAL]": 1.000002482288869,
  "AverageFlitPerStateDelay[DESTINATION_ARRIVED]": 0,
  "MaxFlitPerStateDelay[INPUT_BUFFER]": 18,
  "MaxFlitPerStateDelay[ROUTE_COMPUTATION]": 12,
  "MaxFlitPerStateDelay[VIRTUAL_CHANNEL_ALLOCATION]": 3,
  "MaxFlitPerStateDelay[SWITCH_ALLOCATION]": 1,
  "MaxFlitPerStateDelay[SWITCH_TRAVERSAL]": 1,
  "MaxFlitPerStateDelay[LINK_TRAVERSAL]": 2,
  "MaxFlitPerStateDelay[DESTINATION_ARRIVED]": 0
}