{
  "TotalCycles": 20000,
  "SimulationTime": "25m26.371936745s",
  "CyclesPerSecond": 13.102966268267584,
  "PacketsPerSecond": 44.02072547487178,
  "NumPacketsReceived": 67410,
  "NumPacketsTransmitted": 67192,
  "Throughput": 0.05249375,
  "AveragePacketDelay": 72.0664364805334,
  "AveragePacketHops": 7.021818073580188,
  "MaxPacketDelay": 524,
  "MaxPacketHops": 15,
  "NumPayloadPacketsReceived": 67148,
  "NumPayloadPacketsTransmitted": 66931,
  "PayloadThroughput": 0.05228984375,
  "AveragePayloadPacketDelay": 72.15587694790158,
  "AveragePayloadPacketHops": 7.024562609254307,
  "MaxPayloadPacketDelay": 524,
  "MaxPayloadPacketHops": 15,
  "AverageFlitPerStateDelay[INPUT_BUFFER]": 4.065742989739838,
  "AverageFlitPerStateDelay[ROUTE_COMPUTATION]": 1.632701236343638,
  "AverageFlitPerStateDelay[VIRTUAL_CHANNEL_ALLOCATION]": 1.2454583530765586,
  "AverageFlitPerStateDelay[SWITCH_ALLOCATION]": 1,
  "AverageFlitPerStateDelay[SWITCH_TRAVERSAL]": 1.091278786863538,
  "AverageFlitPerStateDelay[LINK_TRAVERSAL]": 3.3547756326798845,
  "AverageFlitPerStateDelay[DESTINATION_ARRIVED]": 0,
  "MaxFlitPerStateDelay[INPUT_BUFFER]": 87,
  "MaxFlitPerStateDelay[ROUTE_COMPUTATION]": 61,
  "MaxFlitPerStateDelay[VIRTUAL_CHANNEL_ALLOCATION]": 6,
  "MaxFlitPerStateDelay[SWITCH_ALLOCATION]": 1,
  "MaxFlitPerStateDelay[SWITCH_TRAVERSAL]": 60,
  "MaxFlitPerStateDelay[LINK_TRAVERSAL]": 144,
  "MaxFlitPerStateDelay[DESTINATION_ARRIVED]": 0
}